saft_data_mgmt/__init__.py
saft_data_mgmt/__main__.py
saft_data_mgmt/ibkr_utils.py
saft_data_mgmt/ibkr_workflows.py
saft_data_mgmt/models.py
saft_data_mgmt/saft_db.py
saft_data_mgmt/saft_workflows.py
saft_data_mgmt/setup_saft_db.py
saft_data_mgmt/SQLTables/Core/securities_info.sql
saft_data_mgmt/SQLTables/Core/security_exchange.sql
saft_data_mgmt/SQLTables/Core/security_types.sql
saft_data_mgmt/SQLTables/HistoricalPrices/options_ohlcv_float.sql
saft_data_mgmt/SQLTables/HistoricalPrices/options_ohlcv_int.sql
saft_data_mgmt/SQLTables/HistoricalPrices/security_prices_mbp_float.sql
saft_data_mgmt/SQLTables/HistoricalPrices/security_prices_mbp_int.sql
saft_data_mgmt/SQLTables/HistoricalPrices/security_prices_ohlcv_float.sql
saft_data_mgmt/SQLTables/HistoricalPrices/security_prices_ohlcv_int.sql
saft_data_mgmt/SQLTables/HistoricalPrices/security_prices_trade_quotes_float.sql
saft_data_mgmt/SQLTables/HistoricalPrices/security_prices_trade_quotes_int.sql
saft_data_mgmt/SQLTables/PortfolioDB/account_info.sql
saft_data_mgmt/SQLTables/PortfolioDB/all_orders.sql
saft_data_mgmt/SQLTables/PortfolioDB/cancelled_orders.sql
saft_data_mgmt/SQLTables/PortfolioDB/conditional_orders.sql
saft_data_mgmt/SQLTables/PortfolioDB/executed_orders.sql
saft_data_mgmt/SQLTables/PortfolioDB/inference_steps.sql
saft_data_mgmt/SQLTables/PortfolioDB/inference_times.sql
saft_data_mgmt/SQLTables/PortfolioDB/inferences.sql
saft_data_mgmt/SQLTables/PortfolioDB/model_libraries.sql
saft_data_mgmt/SQLTables/PortfolioDB/model_types.sql
saft_data_mgmt/SQLTables/PortfolioDB/models.sql
saft_data_mgmt/SQLTables/PortfolioDB/order_actions.sql
saft_data_mgmt/SQLTables/PortfolioDB/order_types.sql
saft_data_mgmt/SQLTables/PortfolioDB/sessions.sql
saft_data_mgmt/SQLTables/PortfolioDB/strategies.sql
saft_data_mgmt/SQLTables/PortfolioDB/strategy_modules.sql
saft_data_mgmt/SQLTables/PortfolioDB/transaction_types.sql
saft_data_mgmt/SQLTables/PortfolioDB/transactions.sql
saft_data_mgmt-0.2.9.dist-info/licenses/LICENSE
saft_data_mgmt-0.2.9.dist-info/METADATA
saft_data_mgmt-0.2.9.dist-info/WHEEL
saft_data_mgmt-0.2.9.dist-info/entry_points.txt
saft_data_mgmt-0.2.9.dist-info/top_level.txt
saft_data_mgmt-0.2.9.dist-info/RECORD
