Metadata-Version: 2.4
Name: saft_data_mgmt
Version: 0.2.9
Summary: A package for managing financial data, specifically made for algorithmic traders.
Author-email: Travis Swiger <admin@stoneagefinancialtechnology.com>
License:                                  Apache License
Project-URL: Homepage, https://github.com/S-A-F-T-Organization/DataManagement
Classifier: Programming Language :: Python :: 3
Classifier: License :: OSI Approved :: MIT License
Classifier: Operating System :: OS Independent
Classifier: Topic :: Office/Business :: Financial
Classifier: Topic :: Database
Classifier: Development Status :: 3 - Alpha
Requires-Python: >=3.7
License-File: LICENSE
Requires-Dist: SQLAlchemy>=1.4
Requires-Dist: PyYAML
Requires-Dist: ib_insync
Requires-Dist: python-dotenv>=0.21.1
Requires-Dist: twine>=4.0.2
Requires-Dist: build>=1.1.1
Provides-Extra: dev
Requires-Dist: twine>=4.0.2; extra == "dev"
Requires-Dist: build; extra == "dev"
Dynamic: license-file
